{
	"api": {
		"kennyslist": {
			"service": "AppSync",
			"providerPlugin": "awscloudformation",
			"output": {
				"authConfig": {
					"additionalAuthenticationProviders": [],
					"defaultAuthentication": {
						"authenticationType": "API_KEY",
						"apiKeyConfig": {
							"description": "Access to KennysList Services",
							"apiKeyExpirationDays": "365"
						}
					}
				}
			}
		}
	},
	"auth": {
		"kennyslist7144be6d": {
			"service": "Cognito",
			"providerPlugin": "awscloudformation",
			"dependsOn": [],
			"customAuth": false
		}
	},
	"storage": {
		"kennysliststorage": {
			"service": "S3",
			"providerPlugin": "awscloudformation"
		}
	}
}